{
"type": "FeatureCollection",
"name": "SLT_FJ",
"crs": { "type": "name", "properties": { "name": "urn:ogc:def:crs:OGC:1.3:CRS84" } },
"features": [
{ "type": "Feature", "properties": { "FJ NAME": "KL-CL-00001", "LEA": "KL", "TYPE": "Aerial", "Main Sheat Name": null, "Extention_Sheat_Name_1": null, "Extention_Sheat Name_2": null, "Extention_Sheat Name_3": null, "Extention_Sheat Name_4": null, "Extention_Sheat Name_5": null, "Connected EQ Number": null, "REMARKS": null, "Joint Number": "KL-CL-00001", "LAC": null, "Exst_New": "New", "Longitute": 81.787464032517448, "Latitude": 7.4196215041688713 }, "geometry": { "type": "Point", "coordinates": [ 81.787464032517448, 7.419621504168871 ] } }
]
}
